{
  "entityName": "product",
  "displayName": "Product",
  "description": "Information about products and their pricing information.",
  "objectType": "Standard",
  "ownershipType": "OrgOwned",
  "auditEnabled": true,
  "primaryIdField": "productid",
  "primaryNameField": "name",
  "fields": [
    {
      "fieldName": "azt_iscompanion",
      "displayName": "Is Companion",
      "description": "Specifies that the Product is a hardware Companion Product.",
      "dataType": "bit",
      "requiredLevel": "none",
      "isCustom": true,
      "introducedVersion": "1.0.0.0",
      "maxLength": null,
      "fieldSecurity": false,
      "auditEnabled": true,
      "relatedTo": null,
      "picklistValues": [
        {
          "label": "Yes",
          "value": "1"
        },
        {
          "label": "No",
          "value": "0"
        }
      ],
      "sfObjectName": null,
      "sfFieldDisplayName": null,
      "sfFieldApiName": null,
      "sfSuggestedObjectName": "Product2",
      "sfSuggestedFieldDisplayName": "Is Companion",
      "sfSuggestedFieldApiName": "Is_Companion__c",
      "forms": [
        {
          "formName": "Product",
          "formType": "main",
          "formId": "{a640be62-63f6-4027-90d7-48c014a7c6f3}",
          "isActive": true,
          "location": "product_details > product information",
          "label": "Is Companion",
          "visible": "true",
          "disabled": "false"
        }
      ],
      "views": [],
      "chartVisualizations": [],
      "reports": [],
      "dashboards": [],
      "workflows": [],
      "javaScript": [],
      "formulas": [],
      "plugins": [
        {
          "className": "CreateSoftwareLicenses",
          "file": "CreateSoftwareLicenses.cs",
          "targetEntity": "",
          "message": "Update",
          "usage": "read"
        }
      ],
      "pcfControls": [],
      "relationships": [],
      "ribbon": [],
      "conflicts": []
    },
    {
      "fieldName": "azt_isprint",
      "displayName": "Is Print",
      "description": "Determines whether the Product is a Print product for sales line items.",
      "dataType": "bit",
      "requiredLevel": "none",
      "isCustom": true,
      "introducedVersion": "1.0.0.0",
      "maxLength": null,
      "fieldSecurity": false,
      "auditEnabled": true,
      "relatedTo": null,
      "picklistValues": [
        {
          "label": "Yes",
          "value": "1"
        },
        {
          "label": "No",
          "value": "0"
        }
      ],
      "sfObjectName": null,
      "sfFieldDisplayName": null,
      "sfFieldApiName": null,
      "sfSuggestedObjectName": "Product2",
      "sfSuggestedFieldDisplayName": "Is Print",
      "sfSuggestedFieldApiName": "Is_Print__c",
      "forms": [
        {
          "formName": "Product",
          "formType": "main",
          "formId": "{a640be62-63f6-4027-90d7-48c014a7c6f3}",
          "isActive": true,
          "location": "product_details > product information",
          "label": "Print?",
          "visible": "true",
          "disabled": "false"
        }
      ],
      "views": [
        {
          "viewName": "Active Print Products",
          "queryType": "Standard",
          "usage": "filter",
          "operator": "eq",
          "value": "1"
        },
        {
          "viewName": "Active Products",
          "queryType": "Standard",
          "usage": "column",
          "width": "100"
        },
        {
          "viewName": "All Products, Families & Bundles",
          "queryType": "Standard",
          "usage": "column",
          "width": "100"
        }
      ],
      "chartVisualizations": [],
      "reports": [],
      "dashboards": [],
      "workflows": [],
      "javaScript": [
        {
          "file": "azt_opportunityproductlibrary49B3063E-DA1E-EC11-B6E6-000D3A3593EC",
          "usage": [
            "read"
          ]
        },
        {
          "file": "azt_opportunityproductlibrary49B3063E-DA1E-EC11-B6E6-000D3A3593EC",
          "function": "addProduct",
          "usage": [
            "read (WebApi)"
          ]
        }
      ],
      "formulas": [],
      "plugins": [
        {
          "className": "CreateSoftwareLicenses",
          "file": "CreateSoftwareLicenses.cs",
          "targetEntity": "",
          "message": "Update",
          "usage": "read"
        }
      ],
      "pcfControls": [],
      "relationships": [],
      "ribbon": [],
      "conflicts": []
    },
    {
      "fieldName": "azt_nonsaastype",
      "displayName": "Non-SaaS Type",
      "description": "Describes the type of print material the product is e.g. LifeSkills,",
      "dataType": "picklist",
      "requiredLevel": "none",
      "isCustom": true,
      "introducedVersion": "1.0.0.0",
      "maxLength": null,
      "fieldSecurity": false,
      "auditEnabled": true,
      "relatedTo": null,
      "picklistValues": [
        {
          "label": "Kaplan Books",
          "value": "276530001"
        },
        {
          "label": "Life Skills",
          "value": "276530000"
        },
        {
          "label": "GED Vouchers",
          "value": "276530003"
        },
        {
          "label": "Paxen Print",
          "value": "327630000"
        },
        {
          "label": "Other",
          "value": "276530002"
        }
      ],
      "sfObjectName": null,
      "sfFieldDisplayName": null,
      "sfFieldApiName": null,
      "sfSuggestedObjectName": "Product2",
      "sfSuggestedFieldDisplayName": "Non Saas Type",
      "sfSuggestedFieldApiName": "Non_Saas_Type__c",
      "forms": [
        {
          "formName": "Product",
          "formType": "main",
          "formId": "{a640be62-63f6-4027-90d7-48c014a7c6f3}",
          "isActive": true,
          "location": "product_details > product information",
          "label": "Non-SaaS Type",
          "visible": "true",
          "disabled": "false"
        }
      ],
      "views": [],
      "chartVisualizations": [],
      "reports": [],
      "dashboards": [],
      "workflows": [],
      "javaScript": [],
      "formulas": [],
      "plugins": [
        {
          "className": "CreateSoftwareLicenses",
          "file": "CreateSoftwareLicenses.cs",
          "targetEntity": "",
          "message": "Update",
          "usage": "read"
        }
      ],
      "pcfControls": [],
      "relationships": [],
      "ribbon": [],
      "conflicts": []
    },
    {
      "fieldName": "azt_productcategory",
      "displayName": "Product Category",
      "description": "",
      "dataType": "picklist",
      "requiredLevel": "none",
      "isCustom": true,
      "introducedVersion": "1.0.0.0",
      "maxLength": null,
      "fieldSecurity": false,
      "auditEnabled": true,
      "relatedTo": null,
      "picklistValues": [
        {
          "label": "ABE",
          "value": "327630000"
        },
        {
          "label": "HSE",
          "value": "327630001"
        },
        {
          "label": "College",
          "value": "327630002"
        },
        {
          "label": "Healthcare",
          "value": "327630003"
        },
        {
          "label": "Trades",
          "value": "327630004"
        },
        {
          "label": "Life Skills",
          "value": "327630005"
        },
        {
          "label": "Work Skills",
          "value": "327630006"
        }
      ],
      "sfObjectName": null,
      "sfFieldDisplayName": null,
      "sfFieldApiName": null,
      "sfSuggestedObjectName": "Product2",
      "sfSuggestedFieldDisplayName": "Product Type",
      "sfSuggestedFieldApiName": "Product_Type__c",
      "forms": [
        {
          "formName": "Product",
          "formType": "main",
          "formId": "{a640be62-63f6-4027-90d7-48c014a7c6f3}",
          "isActive": true,
          "location": "product_details > product information",
          "label": "Product Category",
          "visible": "true",
          "disabled": "false"
        }
      ],
      "views": [],
      "chartVisualizations": [],
      "reports": [],
      "dashboards": [],
      "workflows": [],
      "javaScript": [],
      "formulas": [],
      "plugins": [],
      "pcfControls": [],
      "relationships": [],
      "ribbon": [],
      "conflicts": [
        {
          "type": "on_forms_not_in_logic"
        }
      ]
    },
    {
      "fieldName": "azt_productfamily",
      "displayName": "Product Family",
      "description": "",
      "dataType": "multiselectpicklist",
      "requiredLevel": "none",
      "isCustom": true,
      "introducedVersion": "1.0.0.0",
      "maxLength": null,
      "fieldSecurity": false,
      "auditEnabled": true,
      "relatedTo": null,
      "picklistValues": null,
      "sfObjectName": null,
      "sfFieldDisplayName": null,
      "sfFieldApiName": null,
      "sfSuggestedObjectName": null,
      "sfSuggestedFieldDisplayName": null,
      "sfSuggestedFieldApiName": null,
      "forms": [
        {
          "formName": "Product",
          "formType": "main",
          "formId": "{a640be62-63f6-4027-90d7-48c014a7c6f3}",
          "isActive": true,
          "location": "product_details > product information",
          "label": "Product Family",
          "visible": "true",
          "disabled": "false"
        }
      ],
      "views": [
        {
          "viewName": "Active Products",
          "queryType": "Standard",
          "usage": "column",
          "width": "150"
        },
        {
          "viewName": "All Products",
          "queryType": "Standard",
          "usage": "column",
          "width": "150"
        }
      ],
      "chartVisualizations": [],
      "reports": [],
      "dashboards": [],
      "workflows": [],
      "javaScript": [],
      "formulas": [],
      "plugins": [],
      "pcfControls": [],
      "relationships": [],
      "ribbon": [],
      "conflicts": []
    },
    {
      "fieldName": "azt_productgroup",
      "displayName": "Product Group",
      "description": "",
      "dataType": "picklist",
      "requiredLevel": "none",
      "isCustom": true,
      "introducedVersion": "1.0.0.0",
      "maxLength": null,
      "fieldSecurity": false,
      "auditEnabled": true,
      "relatedTo": null,
      "picklistValues": [
        {
          "label": "CASAS",
          "value": "327630000"
        },
        {
          "label": "CTE Supplemental",
          "value": "327630007"
        },
        {
          "label": "Comprehensive",
          "value": "327630002"
        },
        {
          "label": "GED Comprehensive",
          "value": "327630008"
        },
        {
          "label": "Credential",
          "value": "327630004"
        },
        {
          "label": "Foundations",
          "value": "327630011"
        },
        {
          "label": "Fundamentals",
          "value": "327630010"
        },
        {
          "label": "GED Supplemental",
          "value": "327630003"
        },
        {
          "label": "HiSET",
          "value": "327630009"
        },
        {
          "label": "Non Re-entry",
          "value": "327630006"
        },
        {
          "label": "Pre-HSE",
          "value": "327630012"
        },
        {
          "label": "Re-entry",
          "value": "327630005"
        },
        {
          "label": "TABE",
          "value": "327630001"
        },
        {
          "label": "Vouchers",
          "value": "327630013"
        },
        {
          "label": "Other",
          "value": "327630014"
        }
      ],
      "sfObjectName": null,
      "sfFieldDisplayName": null,
      "sfFieldApiName": null,
      "sfSuggestedObjectName": null,
      "sfSuggestedFieldDisplayName": null,
      "sfSuggestedFieldApiName": null,
      "forms": [
        {
          "formName": "Product",
          "formType": "main",
          "formId": "{a640be62-63f6-4027-90d7-48c014a7c6f3}",
          "isActive": true,
          "location": "product_details > product information",
          "label": "Product Group",
          "visible": "true",
          "disabled": "false"
        }
      ],
      "views": [],
      "chartVisualizations": [],
      "reports": [],
      "dashboards": [],
      "workflows": [],
      "javaScript": [],
      "formulas": [],
      "plugins": [],
      "pcfControls": [],
      "relationships": [],
      "ribbon": [],
      "conflicts": [
        {
          "type": "on_forms_not_in_logic"
        }
      ]
    },
    {
      "fieldName": "azt_productlanguage",
      "displayName": "Product Language",
      "description": "Language for the Aztec Product",
      "dataType": "picklist",
      "requiredLevel": "none",
      "isCustom": true,
      "introducedVersion": "1.0.0.0",
      "maxLength": null,
      "fieldSecurity": false,
      "auditEnabled": true,
      "relatedTo": null,
      "picklistValues": [
        {
          "label": "English",
          "value": "327630000"
        },
        {
          "label": "Spanish",
          "value": "327630001"
        }
      ],
      "sfObjectName": null,
      "sfFieldDisplayName": null,
      "sfFieldApiName": null,
      "sfSuggestedObjectName": null,
      "sfSuggestedFieldDisplayName": null,
      "sfSuggestedFieldApiName": null,
      "forms": [
        {
          "formName": "Product",
          "formType": "main",
          "formId": "{a640be62-63f6-4027-90d7-48c014a7c6f3}",
          "isActive": true,
          "location": "product_details > product information",
          "label": "Product Language",
          "visible": "true",
          "disabled": "false"
        }
      ],
      "views": [],
      "chartVisualizations": [],
      "reports": [],
      "dashboards": [],
      "workflows": [],
      "javaScript": [],
      "formulas": [],
      "plugins": [],
      "pcfControls": [],
      "relationships": [],
      "ribbon": [],
      "conflicts": [
        {
          "type": "on_forms_not_in_logic"
        }
      ]
    },
    {
      "fieldName": "azt_replacementproductid",
      "displayName": "Replacement Product",
      "description": "Unique identifier of the active product to use as replacement when cloning retired products on opportunities.",
      "dataType": "lookup",
      "requiredLevel": "none",
      "isCustom": true,
      "introducedVersion": "1.0.0.0",
      "maxLength": null,
      "fieldSecurity": false,
      "auditEnabled": false,
      "relatedTo": "Product",
      "picklistValues": null,
      "sfObjectName": null,
      "sfFieldDisplayName": null,
      "sfFieldApiName": null,
      "sfSuggestedObjectName": null,
      "sfSuggestedFieldDisplayName": null,
      "sfSuggestedFieldApiName": null,
      "forms": [
        {
          "formName": "Product",
          "formType": "main",
          "formId": "{a640be62-63f6-4027-90d7-48c014a7c6f3}",
          "isActive": true,
          "location": "price_list_items > msdynsales_pricing_information",
          "label": "Replacement Product",
          "visible": "true",
          "disabled": "false"
        }
      ],
      "views": [],
      "chartVisualizations": [],
      "reports": [],
      "dashboards": [],
      "workflows": [],
      "javaScript": [],
      "formulas": [],
      "plugins": [
        {
          "className": "Utility",
          "file": "Utility.cs",
          "targetEntity": "",
          "message": "",
          "usage": "read"
        }
      ],
      "pcfControls": [],
      "relationships": [
        {
          "relationshipName": "azt_product_product",
          "type": "1:N",
          "referencedEntity": "Product",
          "referencingEntity": "Product"
        }
      ],
      "ribbon": [],
      "conflicts": []
    },
    {
      "fieldName": "azt_saas",
      "displayName": "SAAS",
      "description": "Specifies whether the product is a software",
      "dataType": "bit",
      "requiredLevel": "required",
      "isCustom": true,
      "introducedVersion": "1.0.0.0",
      "maxLength": null,
      "fieldSecurity": false,
      "auditEnabled": true,
      "relatedTo": null,
      "picklistValues": [
        {
          "label": "Yes",
          "value": "1"
        },
        {
          "label": "No",
          "value": "0"
        }
      ],
      "sfObjectName": null,
      "sfFieldDisplayName": null,
      "sfFieldApiName": null,
      "sfSuggestedObjectName": "Product2",
      "sfSuggestedFieldDisplayName": "SaaS",
      "sfSuggestedFieldApiName": "SaaS__c",
      "forms": [
        {
          "formName": "Product",
          "formType": "main",
          "formId": "{a640be62-63f6-4027-90d7-48c014a7c6f3}",
          "isActive": true,
          "location": "product_details > product information",
          "label": "SAAS",
          "visible": "true",
          "disabled": "false"
        }
      ],
      "views": [
        {
          "viewName": "Active Products",
          "queryType": "Standard",
          "usage": "column",
          "width": "100"
        },
        {
          "viewName": "Active SaaS Products",
          "queryType": "Standard",
          "usage": "filter",
          "operator": "eq",
          "value": "1"
        },
        {
          "viewName": "All Products, Families & Bundles",
          "queryType": "Standard",
          "usage": "column",
          "width": "100"
        },
        {
          "viewName": "All Products",
          "queryType": "Standard",
          "usage": "column",
          "width": "100"
        },
        {
          "viewName": "Quick Find All Products",
          "queryType": "Quick Find",
          "usage": "column",
          "width": "100"
        }
      ],
      "chartVisualizations": [],
      "reports": [],
      "dashboards": [],
      "workflows": [],
      "javaScript": [],
      "formulas": [],
      "plugins": [
        {
          "className": "CreateSoftwareLicenses",
          "file": "CreateSoftwareLicenses.cs",
          "targetEntity": "",
          "message": "Update",
          "usage": "read"
        },
        {
          "className": "Utility",
          "file": "Utility.cs",
          "targetEntity": "",
          "message": "",
          "usage": "read"
        }
      ],
      "pcfControls": [],
      "relationships": [],
      "ribbon": [],
      "conflicts": []
    },
    {
      "fieldName": "azt_salesfamily",
      "displayName": "Sales Family",
      "description": "",
      "dataType": "picklist",
      "requiredLevel": "none",
      "isCustom": true,
      "introducedVersion": "1.0.0.0",
      "maxLength": null,
      "fieldSecurity": false,
      "auditEnabled": true,
      "relatedTo": null,
      "picklistValues": [
        {
          "label": "Academic",
          "value": "327630000"
        },
        {
          "label": "Workforce",
          "value": "327630001"
        },
        {
          "label": "Financial Wellness",
          "value": "327630002"
        },
        {
          "label": "CTE",
          "value": "327630003"
        },
        {
          "label": "Other",
          "value": "327630004"
        }
      ],
      "sfObjectName": null,
      "sfFieldDisplayName": null,
      "sfFieldApiName": null,
      "sfSuggestedObjectName": "Product2",
      "sfSuggestedFieldDisplayName": "Sales Family",
      "sfSuggestedFieldApiName": "Sales_Family__c",
      "forms": [
        {
          "formName": "Product",
          "formType": "main",
          "formId": "{a640be62-63f6-4027-90d7-48c014a7c6f3}",
          "isActive": true,
          "location": "product_details > product information",
          "label": "Sales Family",
          "visible": "true",
          "disabled": "false"
        }
      ],
      "views": [],
      "chartVisualizations": [],
      "reports": [],
      "dashboards": [],
      "workflows": [],
      "javaScript": [],
      "formulas": [],
      "plugins": [],
      "pcfControls": [],
      "relationships": [],
      "ribbon": [],
      "conflicts": [
        {
          "type": "on_forms_not_in_logic"
        }
      ]
    },
    {
      "fieldName": "description",
      "displayName": "Description",
      "description": "Description of the product.",
      "dataType": "ntext",
      "requiredLevel": "none",
      "isCustom": false,
      "introducedVersion": "5.0.0.0",
      "maxLength": 2000,
      "fieldSecurity": false,
      "auditEnabled": true,
      "relatedTo": null,
      "picklistValues": null,
      "sfObjectName": null,
      "sfFieldDisplayName": "Description",
      "sfFieldApiName": null,
      "sfSuggestedObjectName": "Product2",
      "sfSuggestedFieldDisplayName": "Description",
      "sfSuggestedFieldApiName": "Description",
      "forms": [],
      "views": [
        {
          "viewName": "Quick Find All Products",
          "queryType": "Quick Find",
          "usage": "column",
          "width": "100"
        }
      ],
      "chartVisualizations": [],
      "reports": [],
      "dashboards": [],
      "workflows": [
        {
          "workflowName": "BatchCancelAppointments",
          "file": "BatchCancelAppointments-DD0A1695-F44B-4C7D-8D09-A0243A22D35B.xaml",
          "usage": "write"
        },
        {
          "workflowName": "BatchCancelPhoneCalls",
          "file": "BatchCancelPhoneCalls-5171315D-5F2E-48D9-8C28-7D946F12CAB9.xaml",
          "usage": "write"
        },
        {
          "workflowName": "BatchOpportunityTransfer",
          "file": "BatchOpportunityTransfer-744FEB80-2251-4252-875E-ED9958CB448A.xaml",
          "usage": "write"
        },
        {
          "workflowName": "CasePendingAssignmentNotification",
          "file": "CasePendingAssignmentNotification-177DE8B3-E0C3-4F1C-A7B5-DA84B3629AED.xaml",
          "usage": "read"
        },
        {
          "workflowName": "CaseRecordOwnerAssignmentNotification",
          "file": "CaseRecordOwnerAssignmentNotification-2F6035E6-1FBC-476B-9C97-4554E8360B7C.xaml",
          "usage": "read"
        },
        {
          "workflowName": "CaseResolutionNotificationEmail",
          "file": "CaseResolutionNotificationEmail-734E721F-7454-4437-8BAC-8B20F496DF12.xaml",
          "usage": "write"
        },
        {
          "workflowName": "CloneOpportunity",
          "file": "CloneOpportunity-1A3FF4B3-79FD-420C-8A10-375E8892CA44.xaml",
          "usage": "write"
        },
        {
          "workflowName": "CloneOrder",
          "file": "CloneOrder-D2A6AD48-A603-4150-BC84-72092AFB3D79.xaml",
          "usage": "write"
        },
        {
          "workflowName": "ExpenseNotificationManager",
          "file": "ExpenseNotificationManager-5CC7F6CC-5991-401F-AEE9-20010EEBB90E.xaml",
          "usage": "write"
        },
        {
          "workflowName": "ExpenseReportRejectedNotification",
          "file": "ExpenseReportRejectedNotification-811FD6D5-D33F-4BEB-8F93-13D7F40F2A78.xaml",
          "usage": "write"
        },
        {
          "workflowName": "FSRLeadDistibutionNotification",
          "file": "FSRLeadDistibutionNotification-2D276CE9-54BF-4703-A56C-933E5C57F3C7.xaml",
          "usage": "write"
        },
        {
          "workflowName": "NewFSRLeadNotification",
          "file": "NewFSRLeadNotification-53E6AF89-E489-4977-8D9F-1579FF72FAC5.xaml",
          "usage": "write"
        },
        {
          "workflowName": "SendQuote",
          "file": "SendQuote-FF6FE214-20D6-4541-AEC6-BD5D18258481.xaml",
          "usage": "write"
        },
        {
          "workflowName": "WonOpportunityEmail",
          "file": "WonOpportunityEmail-DB2872A0-18C2-4157-B6BD-480230C97D32.xaml",
          "usage": "write"
        }
      ],
      "javaScript": [],
      "formulas": [],
      "plugins": [
        {
          "className": "ContactSetConnectionRole",
          "file": "ContactSetConnectionRole.cs",
          "targetEntity": "",
          "message": "azt_ContactSetConnectionRole",
          "usage": "write"
        },
        {
          "className": "OpportunityClone",
          "file": "OpportunityClone.cs",
          "targetEntity": "",
          "message": "Create (inferred)",
          "usage": "read"
        },
        {
          "className": "OrderClone",
          "file": "OrderClone.cs",
          "targetEntity": "",
          "message": "Create (inferred)",
          "usage": "read"
        },
        {
          "className": "OrderSplit",
          "file": "OrderSplit.cs",
          "targetEntity": "",
          "message": "Create (inferred)",
          "usage": "read"
        },
        {
          "className": "OrderSplit",
          "file": "OrderSplit.cs",
          "targetEntity": "",
          "message": "Create (inferred)",
          "usage": "write"
        },
        {
          "className": "PhonecallCreateCallback",
          "file": "PhonecallCreateCallback.cs",
          "targetEntity": "team",
          "message": "Create",
          "usage": "read"
        },
        {
          "className": "SetPrimaryContact",
          "file": "SetPrimaryContact.cs",
          "targetEntity": "",
          "message": "Create",
          "usage": "write"
        }
      ],
      "pcfControls": [],
      "relationships": [],
      "ribbon": [],
      "conflicts": [
        {
          "type": "in_code_not_on_forms"
        }
      ]
    },
    {
      "fieldName": "entityimage",
      "displayName": "Entity Image",
      "description": "Shows the default image for the record.",
      "dataType": "image",
      "requiredLevel": "none",
      "isCustom": false,
      "introducedVersion": "6.0.0.0",
      "maxLength": 9437328,
      "fieldSecurity": false,
      "auditEnabled": false,
      "relatedTo": null,
      "picklistValues": null,
      "sfObjectName": null,
      "sfFieldDisplayName": null,
      "sfFieldApiName": null,
      "sfSuggestedObjectName": null,
      "sfSuggestedFieldDisplayName": null,
      "sfSuggestedFieldApiName": null,
      "forms": [],
      "views": [],
      "chartVisualizations": [],
      "reports": [],
      "dashboards": [],
      "workflows": [],
      "javaScript": [],
      "formulas": [],
      "plugins": [],
      "pcfControls": [],
      "relationships": [],
      "ribbon": [],
      "conflicts": []
    },
    {
      "fieldName": "exchangerate",
      "displayName": "Exchange Rate",
      "description": "Exchange rate for the currency associated with the product with respect to the base currency.",
      "dataType": "decimal",
      "requiredLevel": "none",
      "isCustom": false,
      "introducedVersion": "5.0.0.0",
      "maxLength": null,
      "fieldSecurity": false,
      "auditEnabled": true,
      "relatedTo": null,
      "picklistValues": null,
      "sfObjectName": null,
      "sfFieldDisplayName": null,
      "sfFieldApiName": null,
      "sfSuggestedObjectName": null,
      "sfSuggestedFieldDisplayName": null,
      "sfSuggestedFieldApiName": null,
      "forms": [],
      "views": [],
      "chartVisualizations": [],
      "reports": [],
      "dashboards": [],
      "workflows": [],
      "javaScript": [],
      "formulas": [],
      "plugins": [],
      "pcfControls": [],
      "relationships": [],
      "ribbon": [],
      "conflicts": []
    },
    {
      "fieldName": "hierarchypath",
      "displayName": "Hierarchy Path",
      "description": "Hierarchy path of the product.",
      "dataType": "nvarchar",
      "requiredLevel": "none",
      "isCustom": false,
      "introducedVersion": "7.0.0.0",
      "maxLength": 450,
      "fieldSecurity": false,
      "auditEnabled": true,
      "relatedTo": null,
      "picklistValues": null,
      "sfObjectName": null,
      "sfFieldDisplayName": null,
      "sfFieldApiName": null,
      "sfSuggestedObjectName": null,
      "sfSuggestedFieldDisplayName": null,
      "sfSuggestedFieldApiName": null,
      "forms": [],
      "views": [
        {
          "viewName": "Active Print Products",
          "queryType": "Standard",
          "usage": "column",
          "width": "200"
        },
        {
          "viewName": "Active SaaS Products",
          "queryType": "Standard",
          "usage": "column",
          "width": "200"
        },
        {
          "viewName": "All Products, Families & Bundles",
          "queryType": "Standard",
          "usage": "column",
          "width": "300"
        },
        {
          "viewName": "All Products, Families & Bundles",
          "queryType": "Standard",
          "usage": "sort",
          "descending": false
        },
        {
          "viewName": "Quick Find All Products",
          "queryType": "Quick Find",
          "usage": "column",
          "width": "300"
        }
      ],
      "chartVisualizations": [],
      "reports": [],
      "dashboards": [],
      "workflows": [],
      "javaScript": [],
      "formulas": [],
      "plugins": [],
      "pcfControls": [],
      "relationships": [],
      "ribbon": [],
      "conflicts": []
    },
    {
      "fieldName": "name",
      "displayName": "Name",
      "description": "Name of the product.",
      "dataType": "nvarchar",
      "requiredLevel": "required",
      "isCustom": false,
      "introducedVersion": "5.0.0.0",
      "maxLength": 100,
      "fieldSecurity": false,
      "auditEnabled": true,
      "relatedTo": null,
      "picklistValues": null,
      "sfObjectName": null,
      "sfFieldDisplayName": "Name",
      "sfFieldApiName": null,
      "sfSuggestedObjectName": "Product2",
      "sfSuggestedFieldDisplayName": "Name",
      "sfSuggestedFieldApiName": "Name",
      "forms": [],
      "views": [
        {
          "viewName": "Active Print Products",
          "queryType": "Standard",
          "usage": "column",
          "width": "200"
        },
        {
          "viewName": "Active Print Products",
          "queryType": "Standard",
          "usage": "sort",
          "descending": false
        },
        {
          "viewName": "Active Products",
          "queryType": "Standard",
          "usage": "column",
          "width": "300"
        },
        {
          "viewName": "Active Products",
          "queryType": "Standard",
          "usage": "sort",
          "descending": false
        },
        {
          "viewName": "Active SaaS Products",
          "queryType": "Standard",
          "usage": "column",
          "width": "200"
        },
        {
          "viewName": "Active SaaS Products",
          "queryType": "Standard",
          "usage": "sort",
          "descending": false
        },
        {
          "viewName": "All Products, Families & Bundles",
          "queryType": "Standard",
          "usage": "column",
          "width": "200"
        },
        {
          "viewName": "All Products",
          "queryType": "Standard",
          "usage": "column",
          "width": "200"
        },
        {
          "viewName": "All Products",
          "queryType": "Standard",
          "usage": "sort",
          "descending": false
        },
        {
          "viewName": "Quick Find All Products",
          "queryType": "Quick Find",
          "usage": "column",
          "width": "300"
        },
        {
          "viewName": "Quick Find All Products",
          "queryType": "Quick Find",
          "usage": "filter",
          "operator": "like",
          "value": "{0}"
        },
        {
          "viewName": "Quick Find All Products",
          "queryType": "Quick Find",
          "usage": "sort",
          "descending": false
        }
      ],
      "chartVisualizations": [],
      "reports": [],
      "dashboards": [],
      "workflows": [
        {
          "workflowName": "0EngagementNames",
          "file": "0EngagementNames-BC419DA7-86F1-43E4-88B5-509514704A0C.xaml",
          "usage": "read"
        },
        {
          "workflowName": "BatchConverttoLead",
          "file": "BatchConverttoLead-CC0F2DBB-B8CB-4B06-B891-DB6D97252DB8.xaml",
          "usage": "read"
        },
        {
          "workflowName": "BatchCreateEngagements",
          "file": "BatchCreateEngagements-CC9CDFC6-4BC9-4635-B786-0C7BE2C34344.xaml",
          "usage": "read"
        },
        {
          "workflowName": "BatchLooseOpportunities",
          "file": "BatchLooseOpportunities-BFF14F2D-338D-4CBD-B2CE-C0907E02E6C7.xaml",
          "usage": "read"
        },
        {
          "workflowName": "BatchOpportunityTransfer",
          "file": "BatchOpportunityTransfer-744FEB80-2251-4252-875E-ED9958CB448A.xaml",
          "usage": "read"
        },
        {
          "workflowName": "CloneAndDeleteQuote",
          "file": "CloneAndDeleteQuote-1D87A694-5A08-4C93-9925-447BB4FE7DA6.xaml",
          "usage": "read"
        },
        {
          "workflowName": "CloneOpportunity",
          "file": "CloneOpportunity-1A3FF4B3-79FD-420C-8A10-375E8892CA44.xaml",
          "usage": "read"
        },
        {
          "workflowName": "CloneOrder",
          "file": "CloneOrder-D2A6AD48-A603-4150-BC84-72092AFB3D79.xaml",
          "usage": "read"
        },
        {
          "workflowName": "CreateLeadFromLeadGen",
          "file": "CreateLeadFromLeadGen-2EA14729-4B62-4F91-95FA-76D258DA0831.xaml",
          "usage": "read"
        },
        {
          "workflowName": "CreateLeadfromAccount",
          "file": "CreateLeadfromAccount-B5E04C1C-B038-4018-B602-645B1E766884.xaml",
          "usage": "read"
        },
        {
          "workflowName": "CustomLeadCreation",
          "file": "CustomLeadCreation-B26AC2BB-4660-4A50-9229-AD056DE0D9E1.xaml",
          "usage": "read"
        },
        {
          "workflowName": "NewFSRLeadNotification",
          "file": "NewFSRLeadNotification-53E6AF89-E489-4977-8D9F-1579FF72FAC5.xaml",
          "usage": "read"
        },
        {
          "workflowName": "QualifyLead",
          "file": "QualifyLead-F6899272-F476-48C4-B703-D5ACDD9EDFF7.xaml",
          "usage": "write"
        },
        {
          "workflowName": "RenameEngagements",
          "file": "RenameEngagements-9D4DC906-B3F2-498A-AC17-7D302597E96C.xaml",
          "usage": "read"
        },
        {
          "workflowName": "TaskCreateReorderLead",
          "file": "TaskCreateReorderLead-3193EB56-8E56-46A3-B079-A7CFD1CE90B7.xaml",
          "usage": "read"
        },
        {
          "workflowName": "WonOpportunityEmail",
          "file": "WonOpportunityEmail-DB2872A0-18C2-4157-B6BD-480230C97D32.xaml",
          "usage": "read"
        }
      ],
      "javaScript": [
        {
          "file": "azt_accountlibraryF30D2BCC-3AFA-E811-A983-000D3A1A9151",
          "usage": [
            "read"
          ]
        },
        {
          "file": "azt_accountlibraryF30D2BCC-3AFA-E811-A983-000D3A1A9151",
          "function": "createLead",
          "usage": [
            "read"
          ]
        },
        {
          "file": "azt_accountlibraryF30D2BCC-3AFA-E811-A983-000D3A1A9151",
          "function": "createNewLead",
          "usage": [
            "read"
          ]
        },
        {
          "file": "azt_addresslibrary34ACDB9B-C570-EB11-A812-00224809A7CD",
          "usage": [
            "read"
          ]
        },
        {
          "file": "azt_addresslibrary34ACDB9B-C570-EB11-A812-00224809A7CD",
          "function": "addAddress",
          "usage": [
            "read"
          ]
        },
        {
          "file": "azt_opportunitylibrary43000452-0710-E911-A980-000D3A1A9EFB",
          "usage": [
            "read"
          ]
        },
        {
          "file": "azt_opportunitytrackdiscount8AAC767D-5D0E-E911-A983-000D3A1A9151",
          "usage": [
            "read"
          ]
        },
        {
          "file": "azt_opportunitytrackdiscount8AAC767D-5D0E-E911-A983-000D3A1A9151",
          "function": "trackDiscount",
          "usage": [
            "read"
          ]
        },
        {
          "file": "azt_sendquote0A31A45C-E217-E911-A97D-000D3A1A9FA9",
          "usage": [
            "read"
          ]
        }
      ],
      "formulas": [],
      "plugins": [
        {
          "className": "AccountAutoAssign",
          "file": "AccountAutoAssign.cs",
          "targetEntity": "",
          "message": "Assign (inferred)",
          "usage": "filter"
        },
        {
          "className": "AccountAutoAssign",
          "file": "AccountAutoAssign.cs",
          "targetEntity": "",
          "message": "Assign (inferred)",
          "usage": "sort"
        },
        {
          "className": "AccountReassignmentShareRecords",
          "file": "AccountReassignmentShareRecords.cs",
          "targetEntity": "",
          "message": "GrantAccess (inferred)",
          "usage": "sort"
        },
        {
          "className": "ContactSetConnectionRole",
          "file": "ContactSetConnectionRole.cs",
          "targetEntity": "",
          "message": "azt_ContactSetConnectionRole",
          "usage": "filter"
        },
        {
          "className": "CreateSoftwareLicenses",
          "file": "CreateSoftwareLicenses.cs",
          "targetEntity": "",
          "message": "Update",
          "usage": "read"
        },
        {
          "className": "CreateUserGoals",
          "file": "CreateUserGoals.cs",
          "targetEntity": "",
          "message": "Create (inferred)",
          "usage": "read"
        },
        {
          "className": "CreateUserGoals",
          "file": "CreateUserGoals.cs",
          "targetEntity": "",
          "message": "Create (inferred)",
          "usage": "write"
        },
        {
          "className": "CreateUserGoals",
          "file": "CreateUserGoals.cs",
          "targetEntity": "",
          "message": "Create (inferred)",
          "usage": "filter"
        },
        {
          "className": "GetAcctTeamOwned",
          "file": "GetAcctTeamOwned.cs",
          "targetEntity": "",
          "message": "",
          "usage": "read"
        },
        {
          "className": "GetAcctTeamOwned",
          "file": "GetAcctTeamOwned.cs",
          "targetEntity": "",
          "message": "",
          "usage": "sort"
        },
        {
          "className": "LeadImport",
          "file": "LeadImport.cs",
          "targetEntity": "",
          "message": "Create",
          "usage": "read"
        },
        {
          "className": "LeadImport",
          "file": "LeadImport.cs",
          "targetEntity": "",
          "message": "Create",
          "usage": "filter"
        },
        {
          "className": "LeadImport",
          "file": "LeadImport.cs",
          "targetEntity": "",
          "message": "Create",
          "usage": "sort"
        },
        {
          "className": "LeadQualifyParentStakeholderContacts",
          "file": "LeadQualifyParentStakeholderContacts.cs",
          "targetEntity": "account",
          "message": "Create",
          "usage": "read"
        },
        {
          "className": "OrderSplit",
          "file": "OrderSplit.cs",
          "targetEntity": "",
          "message": "Create (inferred)",
          "usage": "write"
        },
        {
          "className": "PhonecallCreateCallback",
          "file": "PhonecallCreateCallback.cs",
          "targetEntity": "team",
          "message": "Create",
          "usage": "filter"
        },
        {
          "className": "QuoteCloneAndDelete",
          "file": "QuoteCloneAndDelete.cs",
          "targetEntity": "",
          "message": "Delete (inferred)",
          "usage": "sort"
        },
        {
          "className": "RestrictCreateQuote",
          "file": "RestrictCreateQuote.cs",
          "targetEntity": "",
          "message": "Create",
          "usage": "sort"
        },
        {
          "className": "SetPrimaryContact",
          "file": "SetPrimaryContact.cs",
          "targetEntity": "",
          "message": "Create",
          "usage": "read"
        },
        {
          "className": "SetPrimaryContact",
          "file": "SetPrimaryContact.cs",
          "targetEntity": "",
          "message": "Create",
          "usage": "filter"
        },
        {
          "className": "ShareBasedOnAccessTeam",
          "file": "ShareBasedOnAccessTeam.cs",
          "targetEntity": "",
          "message": "GrantAccess (inferred)",
          "usage": "read"
        },
        {
          "className": "ShareFromAccountShares",
          "file": "ShareFromAccountShares.cs",
          "targetEntity": "",
          "message": "Create",
          "usage": "read"
        },
        {
          "className": "Utility",
          "file": "Utility.cs",
          "targetEntity": "",
          "message": "",
          "usage": "read"
        }
      ],
      "pcfControls": [],
      "relationships": [],
      "ribbon": [],
      "conflicts": [
        {
          "type": "in_code_not_on_forms"
        }
      ]
    },
    {
      "fieldName": "price",
      "displayName": "List Price",
      "description": "List price for the product item. Used in price calculations.",
      "dataType": "money",
      "requiredLevel": "none",
      "isCustom": false,
      "introducedVersion": "5.0.0.0",
      "maxLength": null,
      "fieldSecurity": false,
      "auditEnabled": true,
      "relatedTo": null,
      "picklistValues": null,
      "sfObjectName": null,
      "sfFieldDisplayName": null,
      "sfFieldApiName": null,
      "sfSuggestedObjectName": "Product2",
      "sfSuggestedFieldDisplayName": "List Price",
      "sfSuggestedFieldApiName": "List_Price__c",
      "forms": [
        {
          "formName": "Product",
          "formType": "main",
          "formId": "{a640be62-63f6-4027-90d7-48c014a7c6f3}",
          "isActive": true,
          "location": "price_list_items > msdynsales_pricing_information",
          "label": "List Price",
          "visible": "true",
          "disabled": "false"
        }
      ],
      "views": [
        {
          "viewName": "Quick Find All Products",
          "queryType": "Quick Find",
          "usage": "column",
          "width": "100"
        }
      ],
      "chartVisualizations": [],
      "reports": [],
      "dashboards": [],
      "workflows": [],
      "javaScript": [],
      "formulas": [],
      "plugins": [],
      "pcfControls": [],
      "relationships": [],
      "ribbon": [],
      "conflicts": []
    },
    {
      "fieldName": "productnumber",
      "displayName": "Product ID",
      "description": "User-defined product ID.",
      "dataType": "nvarchar",
      "requiredLevel": "systemrequired",
      "isCustom": false,
      "introducedVersion": "5.0.0.0",
      "maxLength": 100,
      "fieldSecurity": false,
      "auditEnabled": true,
      "relatedTo": null,
      "picklistValues": null,
      "sfObjectName": null,
      "sfFieldDisplayName": null,
      "sfFieldApiName": null,
      "sfSuggestedObjectName": "Product2",
      "sfSuggestedFieldDisplayName": "Product Code",
      "sfSuggestedFieldApiName": "ProductCode",
      "forms": [],
      "views": [
        {
          "viewName": "Active Print Products",
          "queryType": "Standard",
          "usage": "column",
          "width": "125"
        },
        {
          "viewName": "Active Products",
          "queryType": "Standard",
          "usage": "column",
          "width": "150"
        },
        {
          "viewName": "Active SaaS Products",
          "queryType": "Standard",
          "usage": "column",
          "width": "125"
        },
        {
          "viewName": "All Products, Families & Bundles",
          "queryType": "Standard",
          "usage": "column",
          "width": "100"
        },
        {
          "viewName": "All Products",
          "queryType": "Standard",
          "usage": "column",
          "width": "150"
        },
        {
          "viewName": "Quick Find All Products",
          "queryType": "Quick Find",
          "usage": "column",
          "width": "100"
        },
        {
          "viewName": "Quick Find All Products",
          "queryType": "Quick Find",
          "usage": "filter",
          "operator": "like",
          "value": "{0}"
        }
      ],
      "chartVisualizations": [],
      "reports": [
        {
          "reportName": "PAQuoteSubReport",
          "dataset": "QuoteLines",
          "entity": "product",
          "usage": "attribute",
          "linkType": "outer",
          "alias": "Product"
        },
        {
          "reportName": "PackingSlipSubReport",
          "dataset": "OrderLines",
          "entity": "product",
          "usage": "attribute",
          "linkType": "outer",
          "alias": "Product"
        },
        {
          "reportName": "SoleSourceLetterSub-Report",
          "dataset": "QuoteLineData",
          "entity": "product",
          "usage": "attribute",
          "linkType": "outer",
          "alias": "Prod"
        },
        {
          "reportName": "SummaryQuoteSubReport",
          "dataset": "QuoteLines",
          "entity": "product",
          "usage": "attribute",
          "linkType": "outer",
          "alias": "ExistingProduct"
        },
        {
          "reportName": "iGradQuoteSubReport",
          "dataset": "OppLines",
          "entity": "product",
          "usage": "attribute",
          "linkType": "outer",
          "alias": "Prod"
        }
      ],
      "dashboards": [],
      "workflows": [],
      "javaScript": [],
      "formulas": [],
      "plugins": [
        {
          "className": "CreateSoftwareLicenses",
          "file": "CreateSoftwareLicenses.cs",
          "targetEntity": "",
          "message": "Update",
          "usage": "read"
        },
        {
          "className": "RestrictProductLookups",
          "file": "RestrictProductLookups.cs",
          "targetEntity": "",
          "message": "RetrieveMultiple",
          "usage": "filter"
        },
        {
          "className": "Utility",
          "file": "Utility.cs",
          "targetEntity": "",
          "message": "",
          "usage": "filter"
        }
      ],
      "pcfControls": [],
      "relationships": [],
      "ribbon": [],
      "conflicts": [
        {
          "type": "in_code_not_on_forms"
        }
      ]
    },
    {
      "fieldName": "productstructure",
      "displayName": "Product Structure",
      "description": "Product Structure.",
      "dataType": "picklist",
      "requiredLevel": "systemrequired",
      "isCustom": false,
      "introducedVersion": "7.0.0.0",
      "maxLength": null,
      "fieldSecurity": false,
      "auditEnabled": true,
      "relatedTo": null,
      "picklistValues": [
        {
          "label": "Product",
          "value": "1"
        },
        {
          "label": "Product Family",
          "value": "2"
        },
        {
          "label": "Product Bundle",
          "value": "3"
        }
      ],
      "sfObjectName": null,
      "sfFieldDisplayName": null,
      "sfFieldApiName": null,
      "sfSuggestedObjectName": null,
      "sfSuggestedFieldDisplayName": null,
      "sfSuggestedFieldApiName": null,
      "forms": [],
      "views": [
        {
          "viewName": "Active Print Products",
          "queryType": "Standard",
          "usage": "column",
          "width": "150"
        },
        {
          "viewName": "Active Products",
          "queryType": "Standard",
          "usage": "filter",
          "operator": "eq",
          "value": "1"
        },
        {
          "viewName": "Active SaaS Products",
          "queryType": "Standard",
          "usage": "column",
          "width": "150"
        },
        {
          "viewName": "All Products, Families & Bundles",
          "queryType": "Standard",
          "usage": "column",
          "width": "110"
        },
        {
          "viewName": "All Products",
          "queryType": "Standard",
          "usage": "filter",
          "operator": "eq",
          "value": "1"
        },
        {
          "viewName": "Quick Find All Products",
          "queryType": "Quick Find",
          "usage": "column",
          "width": "100"
        }
      ],
      "chartVisualizations": [],
      "reports": [],
      "dashboards": [],
      "workflows": [],
      "javaScript": [],
      "formulas": [],
      "plugins": [],
      "pcfControls": [],
      "relationships": [],
      "ribbon": [],
      "conflicts": []
    },
    {
      "fieldName": "producttypecode",
      "displayName": "Product Type",
      "description": "Type of product.",
      "dataType": "picklist",
      "requiredLevel": "none",
      "isCustom": false,
      "introducedVersion": "5.0.0.0",
      "maxLength": null,
      "fieldSecurity": false,
      "auditEnabled": true,
      "relatedTo": null,
      "picklistValues": [
        {
          "label": "Software",
          "value": "1"
        },
        {
          "label": "Legacy",
          "value": "2"
        },
        {
          "label": "Hardware",
          "value": "3"
        },
        {
          "label": "Books",
          "value": "4"
        },
        {
          "label": "Life Skills Book",
          "value": "5"
        },
        {
          "label": "PD",
          "value": "6"
        },
        {
          "label": "Vouchers",
          "value": "8"
        },
        {
          "label": "P6",
          "value": "9"
        },
        {
          "label": "Other",
          "value": "7"
        }
      ],
      "sfObjectName": null,
      "sfFieldDisplayName": null,
      "sfFieldApiName": null,
      "sfSuggestedObjectName": null,
      "sfSuggestedFieldDisplayName": null,
      "sfSuggestedFieldApiName": null,
      "forms": [
        {
          "formName": "Product",
          "formType": "main",
          "formId": "{a640be62-63f6-4027-90d7-48c014a7c6f3}",
          "isActive": true,
          "location": "product_details > product information",
          "label": "Product Type",
          "visible": "true",
          "disabled": "false"
        }
      ],
      "views": [
        {
          "viewName": "Active Print Products",
          "queryType": "Standard",
          "usage": "column",
          "width": "125"
        },
        {
          "viewName": "Active Products",
          "queryType": "Standard",
          "usage": "column",
          "width": "100"
        },
        {
          "viewName": "Active SaaS Products",
          "queryType": "Standard",
          "usage": "column",
          "width": "125"
        },
        {
          "viewName": "All Products, Families & Bundles",
          "queryType": "Standard",
          "usage": "column",
          "width": "100"
        },
        {
          "viewName": "All Products",
          "queryType": "Standard",
          "usage": "column",
          "width": "125"
        },
        {
          "viewName": "Quick Find All Products",
          "queryType": "Quick Find",
          "usage": "column",
          "width": "170"
        }
      ],
      "chartVisualizations": [],
      "reports": [],
      "dashboards": [],
      "workflows": [],
      "javaScript": [],
      "formulas": [],
      "plugins": [
        {
          "className": "OpportunityClone",
          "file": "OpportunityClone.cs",
          "targetEntity": "",
          "message": "Create (inferred)",
          "usage": "read"
        },
        {
          "className": "OrderClone",
          "file": "OrderClone.cs",
          "targetEntity": "",
          "message": "Create (inferred)",
          "usage": "read"
        },
        {
          "className": "OrderSplit",
          "file": "OrderSplit.cs",
          "targetEntity": "",
          "message": "Create (inferred)",
          "usage": "read"
        }
      ],
      "pcfControls": [],
      "relationships": [],
      "ribbon": [],
      "conflicts": []
    },
    {
      "fieldName": "statecode",
      "displayName": "Status",
      "description": "Status of the product.",
      "dataType": "state",
      "requiredLevel": "systemrequired",
      "isCustom": false,
      "introducedVersion": "5.0.0.0",
      "maxLength": null,
      "fieldSecurity": false,
      "auditEnabled": true,
      "relatedTo": null,
      "picklistValues": null,
      "sfObjectName": null,
      "sfFieldDisplayName": null,
      "sfFieldApiName": null,
      "sfSuggestedObjectName": null,
      "sfSuggestedFieldDisplayName": null,
      "sfSuggestedFieldApiName": null,
      "forms": [],
      "views": [
        {
          "viewName": "Active Products",
          "queryType": "Standard",
          "usage": "filter",
          "operator": "eq",
          "value": "0"
        },
        {
          "viewName": "All Products, Families & Bundles",
          "queryType": "Standard",
          "usage": "column",
          "width": "100"
        },
        {
          "viewName": "All Products",
          "queryType": "Standard",
          "usage": "column",
          "width": "100"
        },
        {
          "viewName": "Quick Find All Products",
          "queryType": "Quick Find",
          "usage": "column",
          "width": "100"
        }
      ],
      "chartVisualizations": [],
      "reports": [],
      "dashboards": [],
      "workflows": [
        {
          "workflowName": "BatchConverttoLead",
          "file": "BatchConverttoLead-CC0F2DBB-B8CB-4B06-B891-DB6D97252DB8.xaml",
          "usage": "write"
        },
        {
          "workflowName": "CaseResolutionNotificationEmail",
          "file": "CaseResolutionNotificationEmail-734E721F-7454-4437-8BAC-8B20F496DF12.xaml",
          "usage": "read"
        },
        {
          "workflowName": "CloneOrder",
          "file": "CloneOrder-D2A6AD48-A603-4150-BC84-72092AFB3D79.xaml",
          "usage": "write"
        },
        {
          "workflowName": "CreateLeadFromLeadGen",
          "file": "CreateLeadFromLeadGen-2EA14729-4B62-4F91-95FA-76D258DA0831.xaml",
          "usage": "write"
        },
        {
          "workflowName": "CreateLeadfromAccount",
          "file": "CreateLeadfromAccount-B5E04C1C-B038-4018-B602-645B1E766884.xaml",
          "usage": "write"
        },
        {
          "workflowName": "CustomLeadCreation",
          "file": "CustomLeadCreation-B26AC2BB-4660-4A50-9229-AD056DE0D9E1.xaml",
          "usage": "write"
        },
        {
          "workflowName": "LeadQualifyDisqualifyDate",
          "file": "LeadQualifyDisqualifyDate-4DF6EBF4-0F22-4433-AB4F-A241C91F8B5A.xaml",
          "usage": "read"
        },
        {
          "workflowName": "OpportunityAuditRemoval",
          "file": "OpportunityAuditRemoval-DB05BF90-221B-4B58-8AA0-D1A0799EA0A1.xaml",
          "usage": "read"
        },
        {
          "workflowName": "TaskCreateReorderLead",
          "file": "TaskCreateReorderLead-3193EB56-8E56-46A3-B079-A7CFD1CE90B7.xaml",
          "usage": "write"
        },
        {
          "workflowName": "WonOpportunityEmail",
          "file": "WonOpportunityEmail-DB2872A0-18C2-4157-B6BD-480230C97D32.xaml",
          "usage": "read"
        }
      ],
      "javaScript": [],
      "formulas": [],
      "plugins": [
        {
          "className": "AccountLeadGen",
          "file": "AccountLeadGen.cs",
          "targetEntity": "",
          "message": "Update",
          "usage": "filter"
        },
        {
          "className": "ActivityCloseForceRecordOwner",
          "file": "ActivityCloseForceRecordOwner.cs",
          "targetEntity": "",
          "message": "Update",
          "usage": "read"
        },
        {
          "className": "AllocationValidation",
          "file": "AllocationValidation.cs",
          "targetEntity": "",
          "message": "Create",
          "usage": "filter"
        },
        {
          "className": "ContactSetConnectionRole",
          "file": "ContactSetConnectionRole.cs",
          "targetEntity": "",
          "message": "azt_ContactSetConnectionRole",
          "usage": "read"
        },
        {
          "className": "CreateSoftwareLicenses",
          "file": "CreateSoftwareLicenses.cs",
          "targetEntity": "",
          "message": "Update",
          "usage": "read"
        },
        {
          "className": "CreateSoftwareLicenses",
          "file": "CreateSoftwareLicenses.cs",
          "targetEntity": "",
          "message": "Update",
          "usage": "image"
        },
        {
          "className": "CreateUserGoals",
          "file": "CreateUserGoals.cs",
          "targetEntity": "",
          "message": "Create (inferred)",
          "usage": "filter"
        },
        {
          "className": "DiscretionaryDiscountSetHeader",
          "file": "DiscretionaryDiscountSetHeader.cs",
          "targetEntity": "",
          "message": "Delete",
          "usage": "read"
        },
        {
          "className": "DiscretionaryDiscountSetHeader",
          "file": "DiscretionaryDiscountSetHeader.cs",
          "targetEntity": "",
          "message": "Delete",
          "usage": "filter"
        },
        {
          "className": "ExpenseRestrictVisibility",
          "file": "ExpenseRestrictVisibility.cs",
          "targetEntity": "",
          "message": "",
          "usage": "filter"
        },
        {
          "className": "FundingSetAnnualSpend",
          "file": "FundingSetAnnualSpend.cs",
          "targetEntity": "",
          "message": "Create",
          "usage": "filter"
        },
        {
          "className": "InvoiceClosePaidOnPercentage",
          "file": "InvoiceClosePaidOnPercentage.cs",
          "targetEntity": "",
          "message": "Update",
          "usage": "read"
        },
        {
          "className": "InvoiceCompCompleted",
          "file": "InvoiceCompCompleted.cs",
          "targetEntity": "",
          "message": "Update",
          "usage": "write"
        },
        {
          "className": "LeadImport",
          "file": "LeadImport.cs",
          "targetEntity": "",
          "message": "Create",
          "usage": "filter"
        },
        {
          "className": "OpportunityLineSyncToQuote",
          "file": "OpportunityLineSyncToQuote.cs",
          "targetEntity": "",
          "message": "Update",
          "usage": "read"
        },
        {
          "className": "PhonecallCreateCallback",
          "file": "PhonecallCreateCallback.cs",
          "targetEntity": "team",
          "message": "Create",
          "usage": "read"
        },
        {
          "className": "ProductDiscountPreventOnActiveQuote",
          "file": "ProductDiscountPreventOnActiveQuote.cs",
          "targetEntity": "",
          "message": "Create",
          "usage": "read"
        },
        {
          "className": "RestrictCreateQuote",
          "file": "RestrictCreateQuote.cs",
          "targetEntity": "",
          "message": "Create",
          "usage": "filter"
        },
        {
          "className": "SetPrimaryContact",
          "file": "SetPrimaryContact.cs",
          "targetEntity": "",
          "message": "Create",
          "usage": "read"
        },
        {
          "className": "Utility",
          "file": "Utility.cs",
          "targetEntity": "",
          "message": "",
          "usage": "read"
        }
      ],
      "pcfControls": [],
      "relationships": [],
      "ribbon": [],
      "conflicts": [
        {
          "type": "in_code_not_on_forms"
        }
      ]
    }
  ]
}